django_identity_external-0.8.1.dist-info/licenses/LICENSE
identity/__init__.py
identity/external.py
django_identity_external-0.8.1.dist-info/METADATA
django_identity_external-0.8.1.dist-info/WHEEL
django_identity_external-0.8.1.dist-info/top_level.txt
django_identity_external-0.8.1.dist-info/RECORD
